[
  {
    "id": 0,
    "phone_number": 334463900,
    "turn_of_scan": 5,
    "turn_of_single_play": 0,
    "turn_of_team_play": 5,
    "single_play_level": 5,
    "gems": 3500,
    "grab": "",
    "shopee": ""
  },
  {
    "id": 1,
    "phone_number": 563647211,
    "turn_of_scan": 5,
    "turn_of_single_play": 0,
    "turn_of_team_play": 5,
    "single_play_level": 5,
    "gems": 1410,
    "grab": "",
    "shopee": ""
  },
  {
    "id": 2,
    "phone_number": 583696881,
    "turn_of_scan": 5,
    "turn_of_single_play": 0,
    "turn_of_team_play": 5,
    "single_play_level": 5,
    "gems": 1410,
    "grab": "",
    "shopee": ""
  },
  {
    "id": 3,
    "phone_number": 583664544,
    "turn_of_scan": 5,
    "turn_of_single_play": 0,
    "turn_of_team_play": 5,
    "single_play_level": 5,
    "gems": 1410,
    "grab": "",
    "shopee": ""
  },
  {
    "id": 4,
    "phone_number": 583701556,
    "turn_of_scan": 5,
    "turn_of_single_play": 0,
    "turn_of_team_play": 5,
    "single_play_level": 5,
    "gems": 1410,
    "grab": "",
    "shopee": ""
  },
  {
    "id": 5,
    "phone_number": 583827559,
    "turn_of_scan": 5,
    "turn_of_single_play": 0,
    "turn_of_team_play": 5,
    "single_play_level": 5,
    "gems": 1410,
    "grab": "",
    "shopee": ""
  },
  {
    "id": 6,
    "phone_number": 583645303,
    "turn_of_scan": 5,
    "turn_of_single_play": 0,
    "turn_of_team_play": 5,
    "single_play_level": 5,
    "gems": 1410,
    "grab": "",
    "shopee": ""
  },
  {
    "id": 7,
    "phone_number": 583660019,
    "turn_of_scan": 5,
    "turn_of_single_play": 0,
    "turn_of_team_play": 5,
    "single_play_level": 5,
    "gems": 1410,
    "grab": "",
    "shopee": ""
  },
  {
    "id": 8,
    "phone_number": 583688404,
    "turn_of_scan": 5,
    "turn_of_single_play": 0,
    "turn_of_team_play": 5,
    "single_play_level": 5,
    "gems": 1410,
    "grab": "",
    "shopee": ""
  },
  {
    "id": 9,
    "phone_number": 567733277,
    "turn_of_scan": 5,
    "turn_of_single_play": 0,
    "turn_of_team_play": 5,
    "single_play_level": 5,
    "gems": 1410,
    "grab": "",
    "shopee": ""
  },
  {
    "id": 10,
    "phone_number": 567724821,
    "turn_of_scan": 5,
    "turn_of_single_play": 0,
    "turn_of_team_play": 5,
    "single_play_level": 5,
    "gems": 1410,
    "grab": "",
    "shopee": ""
  },
  {
    "id": 11,
    "phone_number": 567680869,
    "turn_of_scan": 5,
    "turn_of_single_play": 0,
    "turn_of_team_play": 5,
    "single_play_level": 5,
    "gems": 1410,
    "grab": "",
    "shopee": ""
  },
  {
    "id": 12,
    "phone_number": 567929648,
    "turn_of_scan": 5,
    "turn_of_single_play": 0,
    "turn_of_team_play": 5,
    "single_play_level": 5,
    "gems": 1410,
    "grab": "",
    "shopee": ""
  },
  {
    "id": 13,
    "phone_number": 567914183,
    "turn_of_scan": 5,
    "turn_of_single_play": 0,
    "turn_of_team_play": 5,
    "single_play_level": 5,
    "gems": 1410,
    "grab": "",
    "shopee": ""
  },
  {
    "id": 14,
    "phone_number": 567972850,
    "turn_of_scan": 5,
    "turn_of_single_play": 0,
    "turn_of_team_play": 5,
    "single_play_level": 5,
    "gems": 1410,
    "grab": "",
    "shopee": ""
  },
  {
    "id": 15,
    "phone_number": 567694100,
    "turn_of_scan": 5,
    "turn_of_single_play": 0,
    "turn_of_team_play": 5,
    "single_play_level": 5,
    "gems": 1410,
    "grab": "",
    "shopee": ""
  },
  {
    "id": 16,
    "phone_number": 567326802,
    "turn_of_scan": 5,
    "turn_of_single_play": 0,
    "turn_of_team_play": 5,
    "single_play_level": 5,
    "gems": 1410,
    "grab": "",
    "shopee": ""
  },
  {
    "id": 17,
    "phone_number": 353907051,
    "turn_of_scan": 5,
    "turn_of_single_play": 0,
    "turn_of_team_play": 5,
    "single_play_level": 5,
    "gems": 1410,
    "grab": "",
    "shopee": ""
  },
  {
    "id": 18,
    "phone_number": 567326794,
    "turn_of_scan": 5,
    "turn_of_single_play": 0,
    "turn_of_team_play": 5,
    "single_play_level": 5,
    "gems": 1410,
    "grab": "",
    "shopee": ""
  },
  {
    "id": 19,
    "phone_number": 567209119,
    "turn_of_scan": 5,
    "turn_of_single_play": 0,
    "turn_of_team_play": 5,
    "single_play_level": 5,
    "gems": 1410,
    "grab": "",
    "shopee": ""
  },
  {
    "id": 20,
    "phone_number": 567061126,
    "turn_of_scan": 5,
    "turn_of_single_play": 0,
    "turn_of_team_play": 5,
    "single_play_level": 5,
    "gems": 1650,
    "grab": "",
    "shopee": ""
  },
  {
    "id": 21,
    "phone_number": 567372069,
    "turn_of_scan": 5,
    "turn_of_single_play": 0,
    "turn_of_team_play": 5,
    "single_play_level": 5,
    "gems": 1650,
    "grab": "",
    "shopee": ""
  },
  {
    "id": 22,
    "phone_number": 567856462,
    "turn_of_scan": 5,
    "turn_of_single_play": 0,
    "turn_of_team_play": 5,
    "single_play_level": 5,
    "gems": 1650,
    "grab": "",
    "shopee": ""
  },
  {
    "id": 23,
    "phone_number": 567632156,
    "turn_of_scan": 5,
    "turn_of_single_play": 0,
    "turn_of_team_play": 5,
    "single_play_level": 5,
    "gems": 1650,
    "grab": "",
    "shopee": ""
  },
  {
    "id": 24,
    "phone_number": 567098801,
    "turn_of_scan": 5,
    "turn_of_single_play": 0,
    "turn_of_team_play": 5,
    "single_play_level": 5,
    "gems": 1650,
    "grab": "",
    "shopee": ""
  },
  {
    "id": 25,
    "phone_number": 567091850,
    "turn_of_scan": 5,
    "turn_of_single_play": 0,
    "turn_of_team_play": 5,
    "single_play_level": 5,
    "gems": 1410,
    "grab": "",
    "shopee": ""
  },
  {
    "id": 26,
    "phone_number": 567614010,
    "turn_of_scan": 5,
    "turn_of_single_play": 0,
    "turn_of_team_play": 5,
    "single_play_level": 5,
    "gems": 1410,
    "grab": "",
    "shopee": ""
  },
  {
    "id": 27,
    "phone_number": 567188539,
    "turn_of_scan": 5,
    "turn_of_single_play": 0,
    "turn_of_team_play": 5,
    "single_play_level": 5,
    "gems": 1410,
    "grab": "",
    "shopee": ""
  },
  {
    "id": 28,
    "phone_number": 567503278,
    "turn_of_scan": 5,
    "turn_of_single_play": 0,
    "turn_of_team_play": 5,
    "single_play_level": 5,
    "gems": 1410,
    "grab": "",
    "shopee": ""
  },
  {
    "id": 29,
    "phone_number": 384598835,
    "turn_of_scan": 5,
    "turn_of_single_play": 0,
    "turn_of_team_play": 5,
    "single_play_level": 5,
    "gems": 1410,
    "grab": "",
    "shopee": ""
  },
  {
    "id": 30,
    "phone_number": 334626087,
    "turn_of_scan": 5,
    "turn_of_single_play": 0,
    "turn_of_team_play": 5,
    "single_play_level": 5,
    "gems": 1650,
    "grab": "",
    "shopee": ""
  },
  {
    "id": 31,
    "phone_number": 566393033,
    "turn_of_scan": 5,
    "turn_of_single_play": 0,
    "turn_of_team_play": 5,
    "single_play_level": 5,
    "gems": 1650,
    "grab": "",
    "shopee": ""
  },
  {
    "id": 32,
    "phone_number": 566393035,
    "turn_of_scan": 5,
    "turn_of_single_play": 0,
    "turn_of_team_play": 5,
    "single_play_level": 5,
    "gems": 1650,
    "grab": "",
    "shopee": ""
  },
  {
    "id": 33,
    "phone_number": 566391335,
    "turn_of_scan": 5,
    "turn_of_single_play": 0,
    "turn_of_team_play": 5,
    "single_play_level": 5,
    "gems": 1650,
    "grab": "",
    "shopee": ""
  },
  {
    "id": 34,
    "phone_number": 566391323,
    "turn_of_scan": 5,
    "turn_of_single_play": 0,
    "turn_of_team_play": 5,
    "single_play_level": 5,
    "gems": 1650,
    "grab": "",
    "shopee": ""
  },
  {
    "id": 35,
    "phone_number": 566391316,
    "turn_of_scan": 5,
    "turn_of_single_play": 0,
    "turn_of_team_play": 5,
    "single_play_level": 5,
    "gems": 1410,
    "grab": "",
    "shopee": ""
  },
  {
    "id": 36,
    "phone_number": 928480864,
    "turn_of_scan": 5,
    "turn_of_single_play": 0,
    "turn_of_team_play": 5,
    "single_play_level": 5,
    "gems": 1410,
    "grab": "",
    "shopee": ""
  },
  {
    "id": 37,
    "phone_number": 589353068,
    "turn_of_scan": 5,
    "turn_of_single_play": 0,
    "turn_of_team_play": 5,
    "single_play_level": 5,
    "gems": 1410,
    "grab": "",
    "shopee": ""
  },
  {
    "id": 38,
    "phone_number": 588574135,
    "turn_of_scan": 5,
    "turn_of_single_play": 0,
    "turn_of_team_play": 5,
    "single_play_level": 5,
    "gems": 2735,
    "grab": "",
    "shopee": ""
  },
  {
    "id": 39,
    "phone_number": 584986278,
    "turn_of_scan": 5,
    "turn_of_single_play": 0,
    "turn_of_team_play": 5,
    "single_play_level": 5,
    "gems": 3000,
    "grab": "",
    "shopee": ""
  },
  {
    "id": 40,
    "phone_number": 337127229,
    "turn_of_scan": 5,
    "turn_of_single_play": 0,
    "turn_of_team_play": 5,
    "single_play_level": 5,
    "gems": 2635,
    "grab": "",
    "shopee": ""
  },
  {
    "id": 41,
    "phone_number": 565663007,
    "turn_of_scan": 5,
    "turn_of_single_play": 0,
    "turn_of_team_play": 5,
    "single_play_level": 5,
    "gems": 2800,
    "grab": "",
    "shopee": ""
  },
  {
    "id": 42,
    "phone_number": 588154535,
    "turn_of_scan": 5,
    "turn_of_single_play": 0,
    "turn_of_team_play": 5,
    "single_play_level": 5,
    "gems": 2620,
    "grab": "",
    "shopee": ""
  },
  {
    "id": 43,
    "phone_number": 584968193,
    "turn_of_scan": 5,
    "turn_of_single_play": 0,
    "turn_of_team_play": 5,
    "single_play_level": 5,
    "gems": 2350,
    "grab": "",
    "shopee": ""
  },
  {
    "id": 44,
    "phone_number": 567048113,
    "turn_of_scan": 5,
    "turn_of_single_play": 0,
    "turn_of_team_play": 5,
    "single_play_level": 5,
    "gems": 2275,
    "grab": "",
    "shopee": ""
  },
  {
    "id": 45,
    "phone_number": 921606980,
    "turn_of_scan": 5,
    "turn_of_single_play": 0,
    "turn_of_team_play": 5,
    "single_play_level": 5,
    "gems": 2350,
    "grab": "",
    "shopee": ""
  },
  {
    "id": 46,
    "phone_number": 588545829,
    "turn_of_scan": 5,
    "turn_of_single_play": 0,
    "turn_of_team_play": 5,
    "single_play_level": 5,
    "gems": 2350,
    "grab": "",
    "shopee": ""
  },
  {
    "id": 47,
    "phone_number": 588107274,
    "turn_of_scan": 5,
    "turn_of_single_play": 0,
    "turn_of_team_play": 5,
    "single_play_level": 5,
    "gems": 2350,
    "grab": "",
    "shopee": ""
  },
  {
    "id": 48,
    "phone_number": 563918358,
    "turn_of_scan": 5,
    "turn_of_single_play": 0,
    "turn_of_team_play": 5,
    "single_play_level": 5,
    "gems": 2350,
    "grab": "",
    "shopee": ""
  },
  {
    "id": 49,
    "phone_number": 522262310,
    "turn_of_scan": 5,
    "turn_of_single_play": 0,
    "turn_of_team_play": 5,
    "single_play_level": 5,
    "gems": 2350,
    "grab": "",
    "shopee": ""
  },
  {
    "id": 50,
    "phone_number": 588170081,
    "turn_of_scan": 5,
    "turn_of_single_play": 0,
    "turn_of_team_play": 5,
    "single_play_level": 5,
    "gems": 2350,
    "grab": "",
    "shopee": ""
  },
  {
    "id": 51,
    "phone_number": 588551051,
    "turn_of_scan": 5,
    "turn_of_single_play": 0,
    "turn_of_team_play": 5,
    "single_play_level": 5,
    "gems": 2350,
    "grab": "",
    "shopee": ""
  },
  {
    "id": 52,
    "phone_number": 584855377,
    "turn_of_scan": 5,
    "turn_of_single_play": 0,
    "turn_of_team_play": 5,
    "single_play_level": 5,
    "gems": 2350,
    "grab": "",
    "shopee": ""
  },
  {
    "id": 53,
    "phone_number": 588107683,
    "turn_of_scan": 5,
    "turn_of_single_play": 0,
    "turn_of_team_play": 5,
    "single_play_level": 5,
    "gems": 2110,
    "grab": "",
    "shopee": ""
  },
  {
    "id": 54,
    "phone_number": 568687459,
    "turn_of_scan": 5,
    "turn_of_single_play": 0,
    "turn_of_team_play": 5,
    "single_play_level": 5,
    "gems": 1960,
    "grab": "",
    "shopee": ""
  },
  {
    "id": 55,
    "phone_number": 387910925,
    "turn_of_scan": 5,
    "turn_of_single_play": 0,
    "turn_of_team_play": 5,
    "single_play_level": 5,
    "gems": 1650,
    "grab": "",
    "shopee": ""
  },
  {
    "id": 56,
    "phone_number": 373151759,
    "turn_of_scan": 5,
    "turn_of_single_play": 0,
    "turn_of_team_play": 5,
    "single_play_level": 5,
    "gems": 1650,
    "grab": "",
    "shopee": ""
  },
  {
    "id": 57,
    "phone_number": 379539687,
    "turn_of_scan": 5,
    "turn_of_single_play": 0,
    "turn_of_team_play": 5,
    "single_play_level": 5,
    "gems": 1200,
    "grab": "",
    "shopee": ""
  },
  {
    "id": 58,
    "phone_number": 338901339,
    "turn_of_scan": 5,
    "turn_of_single_play": 0,
    "turn_of_team_play": 5,
    "single_play_level": 5,
    "gems": 1200,
    "grab": "",
    "shopee": ""
  },
  {
    "id": 59,
    "phone_number": 376036433,
    "turn_of_scan": 5,
    "turn_of_single_play": 0,
    "turn_of_team_play": 5,
    "single_play_level": 5,
    "gems": 1200,
    "grab": "",
    "shopee": ""
  },
  {
    "id": 60,
    "phone_number": 347508450,
    "turn_of_scan": 5,
    "turn_of_single_play": 0,
    "turn_of_team_play": 5,
    "single_play_level": 5,
    "gems": 1200,
    "grab": "",
    "shopee": ""
  },
  {
    "id": 61,
    "phone_number": 339749943,
    "turn_of_scan": 5,
    "turn_of_single_play": 0,
    "turn_of_team_play": 5,
    "single_play_level": 5,
    "gems": 1200,
    "grab": "",
    "shopee": ""
  },
  {
    "id": 62,
    "phone_number": 342215092,
    "turn_of_scan": 5,
    "turn_of_single_play": 0,
    "turn_of_team_play": 5,
    "single_play_level": 5,
    "gems": 1200,
    "grab": "",
    "shopee": ""
  },
  {
    "id": 63,
    "phone_number": 346816642,
    "turn_of_scan": 5,
    "turn_of_single_play": 0,
    "turn_of_team_play": 5,
    "single_play_level": 5,
    "gems": 1200,
    "grab": "",
    "shopee": ""
  },
  {
    "id": 64,
    "phone_number": 348061005,
    "turn_of_scan": 5,
    "turn_of_single_play": 0,
    "turn_of_team_play": 5,
    "single_play_level": 5,
    "gems": 1200,
    "grab": "",
    "shopee": ""
  },
  {
    "id": 65,
    "phone_number": 867819936,
    "turn_of_scan": 5,
    "turn_of_single_play": 0,
    "turn_of_team_play": 5,
    "single_play_level": 5,
    "gems": 1200,
    "grab": "",
    "shopee": ""
  },
  {
    "id": 66,
    "phone_number": 364769081,
    "turn_of_scan": 5,
    "turn_of_single_play": 0,
    "turn_of_team_play": 5,
    "single_play_level": 5,
    "gems": 1200,
    "grab": "",
    "shopee": ""
  },
  {
    "id": 67,
    "phone_number": 334836801,
    "turn_of_scan": 5,
    "turn_of_single_play": 0,
    "turn_of_team_play": 5,
    "single_play_level": 5,
    "gems": 1200,
    "grab": "",
    "shopee": ""
  },
  {
    "id": 68,
    "phone_number": 338589724,
    "turn_of_scan": 5,
    "turn_of_single_play": 0,
    "turn_of_team_play": 5,
    "single_play_level": 5,
    "gems": 1200,
    "grab": "",
    "shopee": ""
  },
  {
    "id": 69,
    "phone_number": 393635212,
    "turn_of_scan": 5,
    "turn_of_single_play": 0,
    "turn_of_team_play": 5,
    "single_play_level": 5,
    "gems": 1200,
    "grab": "",
    "shopee": ""
  },
  {
    "id": 70,
    "phone_number": 362213735,
    "turn_of_scan": 5,
    "turn_of_single_play": 0,
    "turn_of_team_play": 5,
    "single_play_level": 5,
    "gems": 1200,
    "grab": "",
    "shopee": ""
  },
  {
    "id": 71,
    "phone_number": 332396201,
    "turn_of_scan": 5,
    "turn_of_single_play": 0,
    "turn_of_team_play": 5,
    "single_play_level": 5,
    "gems": 1200,
    "grab": "",
    "shopee": ""
  },
  {
    "id": 72,
    "phone_number": 364416274,
    "turn_of_scan": 5,
    "turn_of_single_play": 0,
    "turn_of_team_play": 5,
    "single_play_level": 5,
    "gems": 1200,
    "grab": "",
    "shopee": ""
  },
  {
    "id": 73,
    "phone_number": 386895400,
    "turn_of_scan": 5,
    "turn_of_single_play": 0,
    "turn_of_team_play": 5,
    "single_play_level": 5,
    "gems": 1200,
    "grab": "",
    "shopee": ""
  },
  {
    "id": 74,
    "phone_number": 383929412,
    "turn_of_scan": 5,
    "turn_of_single_play": 0,
    "turn_of_team_play": 5,
    "single_play_level": 5,
    "gems": 1200,
    "grab": "",
    "shopee": ""
  },
  {
    "id": 75,
    "phone_number": 349978319,
    "turn_of_scan": 5,
    "turn_of_single_play": 0,
    "turn_of_team_play": 5,
    "single_play_level": 5,
    "gems": 1200,
    "grab": "",
    "shopee": ""
  },
  {
    "id": 76,
    "phone_number": 347326921,
    "turn_of_scan": 5,
    "turn_of_single_play": 0,
    "turn_of_team_play": 5,
    "single_play_level": 5,
    "gems": 1200,
    "grab": "",
    "shopee": ""
  },
  {
    "id": 77,
    "phone_number": 329554347,
    "turn_of_scan": 5,
    "turn_of_single_play": 0,
    "turn_of_team_play": 5,
    "single_play_level": 5,
    "gems": 1200,
    "grab": "",
    "shopee": ""
  },
  {
    "id": 78,
    "phone_number": 378280972,
    "turn_of_scan": 5,
    "turn_of_single_play": 0,
    "turn_of_team_play": 5,
    "single_play_level": 5,
    "gems": 1200,
    "grab": "",
    "shopee": ""
  },
  {
    "id": 79,
    "phone_number": 342680504,
    "turn_of_scan": 5,
    "turn_of_single_play": 0,
    "turn_of_team_play": 5,
    "single_play_level": 5,
    "gems": 1200,
    "grab": "",
    "shopee": ""
  },
  {
    "id": 80,
    "phone_number": 342337891,
    "turn_of_scan": 5,
    "turn_of_single_play": 0,
    "turn_of_team_play": 5,
    "single_play_level": 5,
    "gems": 1200,
    "grab": "",
    "shopee": ""
  },
  {
    "id": 81,
    "phone_number": 357758918,
    "turn_of_scan": 5,
    "turn_of_single_play": 0,
    "turn_of_team_play": 5,
    "single_play_level": 5,
    "gems": 1200,
    "grab": "",
    "shopee": ""
  },
  {
    "id": 82,
    "phone_number": 356163231,
    "turn_of_scan": 5,
    "turn_of_single_play": 0,
    "turn_of_team_play": 5,
    "single_play_level": 5,
    "gems": 1200,
    "grab": "",
    "shopee": ""
  },
  {
    "id": 83,
    "phone_number": 566326093,
    "turn_of_scan": 5,
    "turn_of_single_play": 0,
    "turn_of_team_play": 5,
    "single_play_level": 5,
    "gems": 1200,
    "grab": "",
    "shopee": ""
  },
  {
    "id": 84,
    "phone_number": 563452209,
    "turn_of_scan": 5,
    "turn_of_single_play": 0,
    "turn_of_team_play": 5,
    "single_play_level": 5,
    "gems": 1200,
    "grab": "",
    "shopee": ""
  },
  {
    "id": 85,
    "phone_number": 563236488,
    "turn_of_scan": 5,
    "turn_of_single_play": 0,
    "turn_of_team_play": 5,
    "single_play_level": 5,
    "gems": 1200,
    "grab": "",
    "shopee": ""
  },
  {
    "id": 86,
    "phone_number": 563270015,
    "turn_of_scan": 5,
    "turn_of_single_play": 0,
    "turn_of_team_play": 5,
    "single_play_level": 5,
    "gems": 1200,
    "grab": "",
    "shopee": ""
  },
  {
    "id": 87,
    "phone_number": 566325889,
    "turn_of_scan": 5,
    "turn_of_single_play": 0,
    "turn_of_team_play": 5,
    "single_play_level": 5,
    "gems": 1200,
    "grab": "",
    "shopee": ""
  },
  {
    "id": 88,
    "phone_number": 566325905,
    "turn_of_scan": 5,
    "turn_of_single_play": 0,
    "turn_of_team_play": 5,
    "single_play_level": 5,
    "gems": 1200,
    "grab": "",
    "shopee": ""
  },
  {
    "id": 89,
    "phone_number": 566325908,
    "turn_of_scan": 5,
    "turn_of_single_play": 0,
    "turn_of_team_play": 5,
    "single_play_level": 5,
    "gems": 1200,
    "grab": "",
    "shopee": ""
  },
  {
    "id": 90,
    "phone_number": 566326104,
    "turn_of_scan": 5,
    "turn_of_single_play": 0,
    "turn_of_team_play": 5,
    "single_play_level": 5,
    "gems": 1200,
    "grab": "",
    "shopee": ""
  },
  {
    "id": 91,
    "phone_number": 567091391,
    "turn_of_scan": 5,
    "turn_of_single_play": 0,
    "turn_of_team_play": 5,
    "single_play_level": 5,
    "gems": 1200,
    "grab": "",
    "shopee": ""
  },
  {
    "id": 92,
    "phone_number": 567671005,
    "turn_of_scan": 5,
    "turn_of_single_play": 0,
    "turn_of_team_play": 5,
    "single_play_level": 5,
    "gems": 1200,
    "grab": "",
    "shopee": ""
  },
  {
    "id": 93,
    "phone_number": 567972518,
    "turn_of_scan": 5,
    "turn_of_single_play": 0,
    "turn_of_team_play": 5,
    "single_play_level": 5,
    "gems": 1200,
    "grab": "",
    "shopee": ""
  },
  {
    "id": 94,
    "phone_number": 567714401,
    "turn_of_scan": 5,
    "turn_of_single_play": 0,
    "turn_of_team_play": 5,
    "single_play_level": 5,
    "gems": 1200,
    "grab": "",
    "shopee": ""
  },
  {
    "id": 95,
    "phone_number": 567903857,
    "turn_of_scan": 5,
    "turn_of_single_play": 0,
    "turn_of_team_play": 5,
    "single_play_level": 5,
    "gems": 1200,
    "grab": "",
    "shopee": ""
  },
  {
    "id": 96,
    "phone_number": 567245215,
    "turn_of_scan": 5,
    "turn_of_single_play": 0,
    "turn_of_team_play": 5,
    "single_play_level": 5,
    "gems": 1200,
    "grab": "",
    "shopee": ""
  },
  {
    "id": 97,
    "phone_number": 566326094,
    "turn_of_scan": 5,
    "turn_of_single_play": 0,
    "turn_of_team_play": 5,
    "single_play_level": 5,
    "gems": 1200,
    "grab": "",
    "shopee": ""
  },
  {
    "id": 98,
    "phone_number": 567081178,
    "turn_of_scan": 5,
    "turn_of_single_play": 0,
    "turn_of_team_play": 5,
    "single_play_level": 5,
    "gems": 1200,
    "grab": "",
    "shopee": ""
  },
  {
    "id": 99,
    "phone_number": 563731204,
    "turn_of_scan": 5,
    "turn_of_single_play": 0,
    "turn_of_team_play": 5,
    "single_play_level": 5,
    "gems": 1200,
    "grab": "",
    "shopee": ""
  },
  {
    "id": 100,
    "phone_number": 566326274,
    "turn_of_scan": 5,
    "turn_of_single_play": 0,
    "turn_of_team_play": 5,
    "single_play_level": 5,
    "gems": 1200,
    "grab": "",
    "shopee": ""
  },
  {
    "id": 101,
    "phone_number": 566326286,
    "turn_of_scan": 5,
    "turn_of_single_play": 0,
    "turn_of_team_play": 5,
    "single_play_level": 5,
    "gems": 1200,
    "grab": "",
    "shopee": ""
  },
  {
    "id": 102,
    "phone_number": 563145207,
    "turn_of_scan": 5,
    "turn_of_single_play": 0,
    "turn_of_team_play": 5,
    "single_play_level": 5,
    "gems": 1200,
    "grab": "",
    "shopee": ""
  },
  {
    "id": 103,
    "phone_number": 566326086,
    "turn_of_scan": 5,
    "turn_of_single_play": 0,
    "turn_of_team_play": 5,
    "single_play_level": 5,
    "gems": 1200,
    "grab": "",
    "shopee": ""
  },
  {
    "id": 104,
    "phone_number": 566326088,
    "turn_of_scan": 5,
    "turn_of_single_play": 0,
    "turn_of_team_play": 5,
    "single_play_level": 5,
    "gems": 1200,
    "grab": "",
    "shopee": ""
  },
  {
    "id": 105,
    "phone_number": 566326084,
    "turn_of_scan": 5,
    "turn_of_single_play": 0,
    "turn_of_team_play": 5,
    "single_play_level": 5,
    "gems": 1200,
    "grab": "",
    "shopee": ""
  },
  {
    "id": 106,
    "phone_number": 567086358,
    "turn_of_scan": 5,
    "turn_of_single_play": 0,
    "turn_of_team_play": 5,
    "single_play_level": 5,
    "gems": 1200,
    "grab": "",
    "shopee": ""
  },
  {
    "id": 107,
    "phone_number": 567086250,
    "turn_of_scan": 5,
    "turn_of_single_play": 0,
    "turn_of_team_play": 5,
    "single_play_level": 5,
    "gems": 1200,
    "grab": "",
    "shopee": ""
  },
  {
    "id": 108,
    "phone_number": 567086189,
    "turn_of_scan": 5,
    "turn_of_single_play": 0,
    "turn_of_team_play": 5,
    "single_play_level": 5,
    "gems": 1200,
    "grab": "",
    "shopee": ""
  },
  {
    "id": 109,
    "phone_number": 567089057,
    "turn_of_scan": 5,
    "turn_of_single_play": 0,
    "turn_of_team_play": 5,
    "single_play_level": 5,
    "gems": 1200,
    "grab": "",
    "shopee": ""
  },
  {
    "id": 110,
    "phone_number": 982420523,
    "turn_of_scan": 5,
    "turn_of_single_play": 0,
    "turn_of_team_play": 5,
    "single_play_level": 5,
    "gems": 1200,
    "grab": "",
    "shopee": ""
  },
  {
    "id": 111,
    "phone_number": 963093247,
    "turn_of_scan": 5,
    "turn_of_single_play": 0,
    "turn_of_team_play": 5,
    "single_play_level": 5,
    "gems": 1200,
    "grab": "",
    "shopee": ""
  },
  {
    "id": 112,
    "phone_number": 975205604,
    "turn_of_scan": 5,
    "turn_of_single_play": 0,
    "turn_of_team_play": 5,
    "single_play_level": 5,
    "gems": 1200,
    "grab": "",
    "shopee": ""
  },
  {
    "id": 113,
    "phone_number": 355536014,
    "turn_of_scan": 5,
    "turn_of_single_play": 0,
    "turn_of_team_play": 5,
    "single_play_level": 5,
    "gems": 1200,
    "grab": "",
    "shopee": ""
  },
  {
    "id": 114,
    "phone_number": 975186412,
    "turn_of_scan": 5,
    "turn_of_single_play": 0,
    "turn_of_team_play": 5,
    "single_play_level": 5,
    "gems": 1200,
    "grab": "",
    "shopee": ""
  },
  {
    "id": 115,
    "phone_number": 963402521,
    "turn_of_scan": 5,
    "turn_of_single_play": 0,
    "turn_of_team_play": 5,
    "single_play_level": 5,
    "gems": 1200,
    "grab": "",
    "shopee": ""
  },
  {
    "id": 116,
    "phone_number": 389417715,
    "turn_of_scan": 5,
    "turn_of_single_play": 0,
    "turn_of_team_play": 5,
    "single_play_level": 5,
    "gems": 1200,
    "grab": "",
    "shopee": ""
  },
  {
    "id": 117,
    "phone_number": 376650953,
    "turn_of_scan": 5,
    "turn_of_single_play": 0,
    "turn_of_team_play": 5,
    "single_play_level": 5,
    "gems": 1200,
    "grab": "",
    "shopee": ""
  },
  {
    "id": 118,
    "phone_number": 567085982,
    "turn_of_scan": 5,
    "turn_of_single_play": 0,
    "turn_of_team_play": 5,
    "single_play_level": 5,
    "gems": 1200,
    "grab": "",
    "shopee": ""
  },
  {
    "id": 119,
    "phone_number": 589199160,
    "turn_of_scan": 5,
    "turn_of_single_play": 0,
    "turn_of_team_play": 5,
    "single_play_level": 5,
    "gems": 750,
    "grab": "",
    "shopee": ""
  },
  {
    "id": 120,
    "phone_number": 589251759,
    "turn_of_scan": 5,
    "turn_of_single_play": 0,
    "turn_of_team_play": 5,
    "single_play_level": 5,
    "gems": 750,
    "grab": "",
    "shopee": ""
  },
  {
    "id": 121,
    "phone_number": 589218129,
    "turn_of_scan": 5,
    "turn_of_single_play": 0,
    "turn_of_team_play": 5,
    "single_play_level": 5,
    "gems": 750,
    "grab": "",
    "shopee": ""
  },
  {
    "id": 122,
    "phone_number": 563374514,
    "turn_of_scan": 5,
    "turn_of_single_play": 0,
    "turn_of_team_play": 5,
    "single_play_level": 5,
    "gems": 750,
    "grab": "",
    "shopee": ""
  },
  {
    "id": 123,
    "phone_number": 567673575,
    "turn_of_scan": 5,
    "turn_of_single_play": 0,
    "turn_of_team_play": 5,
    "single_play_level": 5,
    "gems": 750,
    "grab": "",
    "shopee": ""
  },
  {
    "id": 124,
    "phone_number": 563287702,
    "turn_of_scan": 5,
    "turn_of_single_play": 0,
    "turn_of_team_play": 5,
    "single_play_level": 5,
    "gems": 750,
    "grab": "",
    "shopee": ""
  },
  {
    "id": 125,
    "phone_number": 567742415,
    "turn_of_scan": 5,
    "turn_of_single_play": 0,
    "turn_of_team_play": 5,
    "single_play_level": 5,
    "gems": 750,
    "grab": "",
    "shopee": ""
  },
  {
    "id": 126,
    "phone_number": 567742543,
    "turn_of_scan": 5,
    "turn_of_single_play": 0,
    "turn_of_team_play": 5,
    "single_play_level": 5,
    "gems": 750,
    "grab": "",
    "shopee": ""
  },
  {
    "id": 127,
    "phone_number": 563174126,
    "turn_of_scan": 5,
    "turn_of_single_play": 0,
    "turn_of_team_play": 5,
    "single_play_level": 5,
    "gems": 750,
    "grab": "",
    "shopee": ""
  },
  {
    "id": 128,
    "phone_number": 567742529,
    "turn_of_scan": 5,
    "turn_of_single_play": 0,
    "turn_of_team_play": 5,
    "single_play_level": 5,
    "gems": 750,
    "grab": "",
    "shopee": ""
  },
  {
    "id": 129,
    "phone_number": 567742560,
    "turn_of_scan": "",
    "turn_of_single_play": "",
    "turn_of_team_play": "",
    "single_play_level": "",
    "gems": "",
    "grab": "",
    "shopee": ""
  },
  {
    "id": 130,
    "phone_number": 563181039,
    "turn_of_scan": 5,
    "turn_of_single_play": 0,
    "turn_of_team_play": 5,
    "single_play_level": 5,
    "gems": 750,
    "grab": "",
    "shopee": ""
  },
  {
    "id": 131,
    "phone_number": 563320378,
    "turn_of_scan": 5,
    "turn_of_single_play": 0,
    "turn_of_team_play": 5,
    "single_play_level": 5,
    "gems": 750,
    "grab": "",
    "shopee": ""
  },
  {
    "id": 132,
    "phone_number": 563604176,
    "turn_of_scan": 5,
    "turn_of_single_play": 0,
    "turn_of_team_play": 5,
    "single_play_level": 5,
    "gems": 750,
    "grab": "",
    "shopee": ""
  },
  {
    "id": 133,
    "phone_number": 563381049,
    "turn_of_scan": 5,
    "turn_of_single_play": 0,
    "turn_of_team_play": 5,
    "single_play_level": 5,
    "gems": 750,
    "grab": "",
    "shopee": ""
  },
  {
    "id": 134,
    "phone_number": 567722359,
    "turn_of_scan": "",
    "turn_of_single_play": "",
    "turn_of_team_play": "",
    "single_play_level": "",
    "gems": "",
    "grab": "",
    "shopee": ""
  },
  {
    "id": 135,
    "phone_number": 567722343,
    "turn_of_scan": 5,
    "turn_of_single_play": 0,
    "turn_of_team_play": 5,
    "single_play_level": 5,
    "gems": 750,
    "grab": "",
    "shopee": ""
  },
  {
    "id": 136,
    "phone_number": 567081042,
    "turn_of_scan": 5,
    "turn_of_single_play": 0,
    "turn_of_team_play": 5,
    "single_play_level": 5,
    "gems": 750,
    "grab": "",
    "shopee": ""
  },
  {
    "id": 137,
    "phone_number": 587715528,
    "turn_of_scan": 5,
    "turn_of_single_play": 0,
    "turn_of_team_play": 5,
    "single_play_level": 5,
    "gems": 750,
    "grab": "",
    "shopee": ""
  },
  {
    "id": 138,
    "phone_number": 587715631,
    "turn_of_scan": 5,
    "turn_of_single_play": 0,
    "turn_of_team_play": 5,
    "single_play_level": 5,
    "gems": 750,
    "grab": "",
    "shopee": ""
  },
  {
    "id": 139,
    "phone_number": 587715446,
    "turn_of_scan": 5,
    "turn_of_single_play": 0,
    "turn_of_team_play": 5,
    "single_play_level": 5,
    "gems": 750,
    "grab": "",
    "shopee": ""
  },
  {
    "id": 140,
    "phone_number": 587715516,
    "turn_of_scan": 5,
    "turn_of_single_play": 0,
    "turn_of_team_play": 5,
    "single_play_level": 5,
    "gems": 750,
    "grab": "",
    "shopee": ""
  },
  {
    "id": 141,
    "phone_number": 587715672,
    "turn_of_scan": 5,
    "turn_of_single_play": 0,
    "turn_of_team_play": 5,
    "single_play_level": 5,
    "gems": 750,
    "grab": "",
    "shopee": ""
  },
  {
    "id": 142,
    "phone_number": 587715514,
    "turn_of_scan": 5,
    "turn_of_single_play": 0,
    "turn_of_team_play": 5,
    "single_play_level": 5,
    "gems": 750,
    "grab": "",
    "shopee": ""
  },
  {
    "id": 143,
    "phone_number": 587715502,
    "turn_of_scan": 5,
    "turn_of_single_play": 0,
    "turn_of_team_play": 5,
    "single_play_level": 5,
    "gems": 750,
    "grab": "",
    "shopee": ""
  },
  {
    "id": 144,
    "phone_number": 587715643,
    "turn_of_scan": 5,
    "turn_of_single_play": 0,
    "turn_of_team_play": 5,
    "single_play_level": 5,
    "gems": 750,
    "grab": "",
    "shopee": ""
  },
  {
    "id": 145,
    "phone_number": 587715638,
    "turn_of_scan": 5,
    "turn_of_single_play": 0,
    "turn_of_team_play": 5,
    "single_play_level": 5,
    "gems": 750,
    "grab": "",
    "shopee": ""
  },
  {
    "id": 146,
    "phone_number": 587715407,
    "turn_of_scan": 5,
    "turn_of_single_play": 0,
    "turn_of_team_play": 5,
    "single_play_level": 5,
    "gems": 750,
    "grab": "",
    "shopee": ""
  },
  {
    "id": 147,
    "phone_number": 587715671,
    "turn_of_scan": "",
    "turn_of_single_play": "",
    "turn_of_team_play": "",
    "single_play_level": "",
    "gems": "",
    "grab": "",
    "shopee": ""
  },
  {
    "id": 148,
    "phone_number": 587715404,
    "turn_of_scan": 5,
    "turn_of_single_play": 0,
    "turn_of_team_play": 5,
    "single_play_level": 5,
    "gems": 750,
    "grab": "",
    "shopee": ""
  },
  {
    "id": 149,
    "phone_number": 587715663,
    "turn_of_scan": "",
    "turn_of_single_play": "",
    "turn_of_team_play": "",
    "single_play_level": "",
    "gems": "",
    "grab": "",
    "shopee": ""
  },
  {
    "id": 150,
    "phone_number": 587715399,
    "turn_of_scan": 5,
    "turn_of_single_play": 0,
    "turn_of_team_play": 5,
    "single_play_level": 5,
    "gems": 750,
    "grab": "",
    "shopee": ""
  },
  {
    "id": 151,
    "phone_number": 587715408,
    "turn_of_scan": 5,
    "turn_of_single_play": 0,
    "turn_of_team_play": 5,
    "single_play_level": 5,
    "gems": 750,
    "grab": "",
    "shopee": ""
  },
  {
    "id": 152,
    "phone_number": 587715603,
    "turn_of_scan": "",
    "turn_of_single_play": "",
    "turn_of_team_play": "",
    "single_play_level": "",
    "gems": "",
    "grab": "",
    "shopee": ""
  },
  {
    "id": 153,
    "phone_number": 587715413,
    "turn_of_scan": 5,
    "turn_of_single_play": 0,
    "turn_of_team_play": 5,
    "single_play_level": 5,
    "gems": 750,
    "grab": "",
    "shopee": ""
  },
  {
    "id": 154,
    "phone_number": 587715601,
    "turn_of_scan": 5,
    "turn_of_single_play": 0,
    "turn_of_team_play": 5,
    "single_play_level": 5,
    "gems": 750,
    "grab": "",
    "shopee": ""
  },
  {
    "id": 155,
    "phone_number": 587715598,
    "turn_of_scan": "",
    "turn_of_single_play": "",
    "turn_of_team_play": "",
    "single_play_level": "",
    "gems": "",
    "grab": "",
    "shopee": ""
  },
  {
    "id": 156,
    "phone_number": 587714592,
    "turn_of_scan": 5,
    "turn_of_single_play": 0,
    "turn_of_team_play": 5,
    "single_play_level": 5,
    "gems": 750,
    "grab": "",
    "shopee": ""
  },
  {
    "id": 157,
    "phone_number": 587663861,
    "turn_of_scan": 5,
    "turn_of_single_play": 0,
    "turn_of_team_play": 5,
    "single_play_level": 5,
    "gems": 750,
    "grab": "",
    "shopee": ""
  },
  {
    "id": 158,
    "phone_number": 587715652,
    "turn_of_scan": 5,
    "turn_of_single_play": 0,
    "turn_of_team_play": 5,
    "single_play_level": 5,
    "gems": 750,
    "grab": "",
    "shopee": ""
  },
  {
    "id": 159,
    "phone_number": 587663940,
    "turn_of_scan": 5,
    "turn_of_single_play": 0,
    "turn_of_team_play": 5,
    "single_play_level": 5,
    "gems": 750,
    "grab": "",
    "shopee": ""
  },
  {
    "id": 160,
    "phone_number": 587714482,
    "turn_of_scan": 5,
    "turn_of_single_play": 0,
    "turn_of_team_play": 5,
    "single_play_level": 5,
    "gems": 750,
    "grab": "",
    "shopee": ""
  },
  {
    "id": 161,
    "phone_number": 587714857,
    "turn_of_scan": 5,
    "turn_of_single_play": 0,
    "turn_of_team_play": 5,
    "single_play_level": 5,
    "gems": 750,
    "grab": "",
    "shopee": ""
  },
  {
    "id": 162,
    "phone_number": 587714289,
    "turn_of_scan": 5,
    "turn_of_single_play": 0,
    "turn_of_team_play": 5,
    "single_play_level": 5,
    "gems": 750,
    "grab": "",
    "shopee": ""
  },
  {
    "id": 163,
    "phone_number": 587714708,
    "turn_of_scan": 5,
    "turn_of_single_play": 0,
    "turn_of_team_play": 5,
    "single_play_level": 5,
    "gems": 750,
    "grab": "",
    "shopee": ""
  },
  {
    "id": 164,
    "phone_number": 587714276,
    "turn_of_scan": "",
    "turn_of_single_play": "",
    "turn_of_team_play": "",
    "single_play_level": "",
    "gems": "",
    "grab": "",
    "shopee": ""
  },
  {
    "id": 165,
    "phone_number": 393195948,
    "turn_of_scan": "",
    "turn_of_single_play": "",
    "turn_of_team_play": "",
    "single_play_level": "",
    "gems": "",
    "grab": "",
    "shopee": ""
  },
  {
    "id": 166,
    "phone_number": 964867432,
    "turn_of_scan": "",
    "turn_of_single_play": "",
    "turn_of_team_play": "",
    "single_play_level": "",
    "gems": "",
    "grab": "",
    "shopee": ""
  },
  {
    "id": 167,
    "phone_number": 365384689,
    "turn_of_scan": "",
    "turn_of_single_play": "",
    "turn_of_team_play": "",
    "single_play_level": "",
    "gems": "",
    "grab": "",
    "shopee": ""
  },
  {
    "id": 168,
    "phone_number": 582306993,
    "turn_of_scan": "",
    "turn_of_single_play": "",
    "turn_of_team_play": "",
    "single_play_level": "",
    "gems": "",
    "grab": "",
    "shopee": ""
  },
  {
    "id": 169,
    "phone_number": 582357040,
    "turn_of_scan": "",
    "turn_of_single_play": "",
    "turn_of_team_play": "",
    "single_play_level": "",
    "gems": "",
    "grab": "",
    "shopee": ""
  },
  {
    "id": 170,
    "phone_number": 582264484,
    "turn_of_scan": "",
    "turn_of_single_play": "",
    "turn_of_team_play": "",
    "single_play_level": "",
    "gems": "",
    "grab": "",
    "shopee": ""
  },
  {
    "id": 171,
    "phone_number": 582191681,
    "turn_of_scan": "",
    "turn_of_single_play": "",
    "turn_of_team_play": "",
    "single_play_level": "",
    "gems": "",
    "grab": "",
    "shopee": ""
  },
  {
    "id": 172,
    "phone_number": 582215292,
    "turn_of_scan": "",
    "turn_of_single_play": "",
    "turn_of_team_play": "",
    "single_play_level": "",
    "gems": "",
    "grab": "",
    "shopee": ""
  },
  {
    "id": 173,
    "phone_number": 582190409,
    "turn_of_scan": "",
    "turn_of_single_play": "",
    "turn_of_team_play": "",
    "single_play_level": "",
    "gems": "",
    "grab": "",
    "shopee": ""
  },
  {
    "id": 174,
    "phone_number": 582338227,
    "turn_of_scan": "",
    "turn_of_single_play": "",
    "turn_of_team_play": "",
    "single_play_level": "",
    "gems": "",
    "grab": "",
    "shopee": ""
  },
  {
    "id": 175,
    "phone_number": 582217765,
    "turn_of_scan": "",
    "turn_of_single_play": "",
    "turn_of_team_play": "",
    "single_play_level": "",
    "gems": "",
    "grab": "",
    "shopee": ""
  },
  {
    "id": 176,
    "phone_number": 582316338,
    "turn_of_scan": "",
    "turn_of_single_play": "",
    "turn_of_team_play": "",
    "single_play_level": "",
    "gems": "",
    "grab": "",
    "shopee": ""
  },
  {
    "id": 177,
    "phone_number": 582318180,
    "turn_of_scan": "",
    "turn_of_single_play": "",
    "turn_of_team_play": "",
    "single_play_level": "",
    "gems": "",
    "grab": "",
    "shopee": ""
  },
  {
    "id": 178,
    "phone_number": 582338183,
    "turn_of_scan": "",
    "turn_of_single_play": "",
    "turn_of_team_play": "",
    "single_play_level": "",
    "gems": "",
    "grab": "",
    "shopee": ""
  },
  {
    "id": 179,
    "phone_number": 582351043,
    "turn_of_scan": "",
    "turn_of_single_play": "",
    "turn_of_team_play": "",
    "single_play_level": "",
    "gems": "",
    "grab": "",
    "shopee": ""
  },
  {
    "id": 180,
    "phone_number": 582230754,
    "turn_of_scan": "",
    "turn_of_single_play": "",
    "turn_of_team_play": "",
    "single_play_level": "",
    "gems": "",
    "grab": "",
    "shopee": ""
  },
  {
    "id": 181,
    "phone_number": 582268734,
    "turn_of_scan": "",
    "turn_of_single_play": "",
    "turn_of_team_play": "",
    "single_play_level": "",
    "gems": "",
    "grab": "",
    "shopee": ""
  },
  {
    "id": 182,
    "phone_number": 582309774,
    "turn_of_scan": "",
    "turn_of_single_play": "",
    "turn_of_team_play": "",
    "single_play_level": "",
    "gems": "",
    "grab": "",
    "shopee": ""
  },
  {
    "id": 183,
    "phone_number": 582272083,
    "turn_of_scan": "",
    "turn_of_single_play": "",
    "turn_of_team_play": "",
    "single_play_level": "",
    "gems": "",
    "grab": "",
    "shopee": ""
  },
  {
    "id": 184,
    "phone_number": 582297597,
    "turn_of_scan": "",
    "turn_of_single_play": "",
    "turn_of_team_play": "",
    "single_play_level": "",
    "gems": "",
    "grab": "",
    "shopee": ""
  },
  {
    "id": 185,
    "phone_number": 582319895,
    "turn_of_scan": "",
    "turn_of_single_play": "",
    "turn_of_team_play": "",
    "single_play_level": "",
    "gems": "",
    "grab": "",
    "shopee": ""
  },
  {
    "id": 186,
    "phone_number": 582297461,
    "turn_of_scan": "",
    "turn_of_single_play": "",
    "turn_of_team_play": "",
    "single_play_level": "",
    "gems": "",
    "grab": "",
    "shopee": ""
  },
  {
    "id": 187,
    "phone_number": 582346537,
    "turn_of_scan": "",
    "turn_of_single_play": "",
    "turn_of_team_play": "",
    "single_play_level": "",
    "gems": "",
    "grab": "",
    "shopee": ""
  },
  {
    "id": 188,
    "phone_number": 582311905,
    "turn_of_scan": "",
    "turn_of_single_play": "",
    "turn_of_team_play": "",
    "single_play_level": "",
    "gems": "",
    "grab": "",
    "shopee": ""
  },
  {
    "id": 189,
    "phone_number": 582338025,
    "turn_of_scan": "",
    "turn_of_single_play": "",
    "turn_of_team_play": "",
    "single_play_level": "",
    "gems": "",
    "grab": "",
    "shopee": ""
  },
  {
    "id": 190,
    "phone_number": 582201900,
    "turn_of_scan": "",
    "turn_of_single_play": "",
    "turn_of_team_play": "",
    "single_play_level": "",
    "gems": "",
    "grab": "",
    "shopee": ""
  },
  {
    "id": 191,
    "phone_number": 582181461,
    "turn_of_scan": "",
    "turn_of_single_play": "",
    "turn_of_team_play": "",
    "single_play_level": "",
    "gems": "",
    "grab": "",
    "shopee": ""
  },
  {
    "id": 192,
    "phone_number": 582318503,
    "turn_of_scan": "",
    "turn_of_single_play": "",
    "turn_of_team_play": "",
    "single_play_level": "",
    "gems": "",
    "grab": "",
    "shopee": ""
  },
  {
    "id": 193,
    "phone_number": 582339275,
    "turn_of_scan": "",
    "turn_of_single_play": "",
    "turn_of_team_play": "",
    "single_play_level": "",
    "gems": "",
    "grab": "",
    "shopee": ""
  },
  {
    "id": 194,
    "phone_number": 582268783,
    "turn_of_scan": "",
    "turn_of_single_play": "",
    "turn_of_team_play": "",
    "single_play_level": "",
    "gems": "",
    "grab": "",
    "shopee": ""
  },
  {
    "id": 195,
    "phone_number": 582251350,
    "turn_of_scan": "",
    "turn_of_single_play": "",
    "turn_of_team_play": "",
    "single_play_level": "",
    "gems": "",
    "grab": "",
    "shopee": ""
  },
  {
    "id": 196,
    "phone_number": 582343820,
    "turn_of_scan": "",
    "turn_of_single_play": "",
    "turn_of_team_play": "",
    "single_play_level": "",
    "gems": "",
    "grab": "",
    "shopee": ""
  },
  {
    "id": 197,
    "phone_number": 582285184,
    "turn_of_scan": "",
    "turn_of_single_play": "",
    "turn_of_team_play": "",
    "single_play_level": "",
    "gems": "",
    "grab": "",
    "shopee": ""
  },
  {
    "id": 198,
    "phone_number": 582330197,
    "turn_of_scan": "",
    "turn_of_single_play": "",
    "turn_of_team_play": "",
    "single_play_level": "",
    "gems": "",
    "grab": "",
    "shopee": ""
  },
  {
    "id": 199,
    "phone_number": 582349737,
    "turn_of_scan": "",
    "turn_of_single_play": "",
    "turn_of_team_play": "",
    "single_play_level": "",
    "gems": "",
    "grab": "",
    "shopee": ""
  },
  {
    "id": 200,
    "phone_number": 582262144,
    "turn_of_scan": "",
    "turn_of_single_play": "",
    "turn_of_team_play": "",
    "single_play_level": "",
    "gems": "",
    "grab": "",
    "shopee": ""
  },
  {
    "id": 201,
    "phone_number": 582201650,
    "turn_of_scan": "",
    "turn_of_single_play": "",
    "turn_of_team_play": "",
    "single_play_level": "",
    "gems": "",
    "grab": "",
    "shopee": ""
  },
  {
    "id": 202,
    "phone_number": 582307365,
    "turn_of_scan": "",
    "turn_of_single_play": "",
    "turn_of_team_play": "",
    "single_play_level": "",
    "gems": "",
    "grab": "",
    "shopee": ""
  },
  {
    "id": 203,
    "phone_number": 582315576,
    "turn_of_scan": "",
    "turn_of_single_play": "",
    "turn_of_team_play": "",
    "single_play_level": "",
    "gems": "",
    "grab": "",
    "shopee": ""
  },
  {
    "id": 204,
    "phone_number": 582360601,
    "turn_of_scan": "",
    "turn_of_single_play": "",
    "turn_of_team_play": "",
    "single_play_level": "",
    "gems": "",
    "grab": "",
    "shopee": ""
  },
  {
    "id": 205,
    "phone_number": 582279187,
    "turn_of_scan": "",
    "turn_of_single_play": "",
    "turn_of_team_play": "",
    "single_play_level": "",
    "gems": "",
    "grab": "",
    "shopee": ""
  },
  {
    "id": 206,
    "phone_number": 582191186,
    "turn_of_scan": "",
    "turn_of_single_play": "",
    "turn_of_team_play": "",
    "single_play_level": "",
    "gems": "",
    "grab": "",
    "shopee": ""
  },
  {
    "id": 207,
    "phone_number": 582273973,
    "turn_of_scan": "",
    "turn_of_single_play": "",
    "turn_of_team_play": "",
    "single_play_level": "",
    "gems": "",
    "grab": "",
    "shopee": ""
  },
  {
    "id": 208,
    "phone_number": 582210301,
    "turn_of_scan": "",
    "turn_of_single_play": "",
    "turn_of_team_play": "",
    "single_play_level": "",
    "gems": "",
    "grab": "",
    "shopee": ""
  },
  {
    "id": 209,
    "phone_number": 582290781,
    "turn_of_scan": "",
    "turn_of_single_play": "",
    "turn_of_team_play": "",
    "single_play_level": "",
    "gems": "",
    "grab": "",
    "shopee": ""
  },
  {
    "id": 210,
    "phone_number": 582297653,
    "turn_of_scan": "",
    "turn_of_single_play": "",
    "turn_of_team_play": "",
    "single_play_level": "",
    "gems": "",
    "grab": "",
    "shopee": ""
  },
  {
    "id": 211,
    "phone_number": 582318428,
    "turn_of_scan": "",
    "turn_of_single_play": "",
    "turn_of_team_play": "",
    "single_play_level": "",
    "gems": "",
    "grab": "",
    "shopee": ""
  },
  {
    "id": 212,
    "phone_number": 582249170,
    "turn_of_scan": "",
    "turn_of_single_play": "",
    "turn_of_team_play": "",
    "single_play_level": "",
    "gems": "",
    "grab": "",
    "shopee": ""
  },
  {
    "id": 213,
    "phone_number": 582183581,
    "turn_of_scan": "",
    "turn_of_single_play": "",
    "turn_of_team_play": "",
    "single_play_level": "",
    "gems": "",
    "grab": "",
    "shopee": ""
  },
  {
    "id": 214,
    "phone_number": 582206527,
    "turn_of_scan": "",
    "turn_of_single_play": "",
    "turn_of_team_play": "",
    "single_play_level": "",
    "gems": "",
    "grab": "",
    "shopee": ""
  },
  {
    "id": 215,
    "phone_number": 582347075,
    "turn_of_scan": "",
    "turn_of_single_play": "",
    "turn_of_team_play": "",
    "single_play_level": "",
    "gems": "",
    "grab": "",
    "shopee": ""
  },
  {
    "id": 216,
    "phone_number": 582319679,
    "turn_of_scan": "",
    "turn_of_single_play": "",
    "turn_of_team_play": "",
    "single_play_level": "",
    "gems": "",
    "grab": "",
    "shopee": ""
  },
  {
    "id": 217,
    "phone_number": 582334131,
    "turn_of_scan": "",
    "turn_of_single_play": "",
    "turn_of_team_play": "",
    "single_play_level": "",
    "gems": "",
    "grab": "",
    "shopee": ""
  },
  {
    "id": 218,
    "phone_number": 582321686,
    "turn_of_scan": "",
    "turn_of_single_play": "",
    "turn_of_team_play": "",
    "single_play_level": "",
    "gems": "",
    "grab": "",
    "shopee": ""
  },
  {
    "id": 219,
    "phone_number": 582308677,
    "turn_of_scan": "",
    "turn_of_single_play": "",
    "turn_of_team_play": "",
    "single_play_level": "",
    "gems": "",
    "grab": "",
    "shopee": ""
  },
  {
    "id": 220,
    "phone_number": 582332118,
    "turn_of_scan": "",
    "turn_of_single_play": "",
    "turn_of_team_play": "",
    "single_play_level": "",
    "gems": "",
    "grab": "",
    "shopee": ""
  },
  {
    "id": 221,
    "phone_number": 582313953,
    "turn_of_scan": "",
    "turn_of_single_play": "",
    "turn_of_team_play": "",
    "single_play_level": "",
    "gems": "",
    "grab": "",
    "shopee": ""
  },
  {
    "id": 222,
    "phone_number": 582268810,
    "turn_of_scan": "",
    "turn_of_single_play": "",
    "turn_of_team_play": "",
    "single_play_level": "",
    "gems": "",
    "grab": "",
    "shopee": ""
  }
]